[{"temp":"26","hum":"26","duty":"512","lastEntry":"2018-10-11T09:17:57.478Z","hash":"zJf3yuQpJN"},{"temp":"26","hum":"25","duty":"512","lastEntry":"2018-10-11T09:18:15.497Z","hash":"TRzFRMiWa4"},{"temp":"26","hum":"26","duty":"512","lastEntry":"2018-10-11T09:18:30.923Z","hash":"AVVLB54cnJ"},{"temp":"26","hum":"26","duty":"512","lastEntry":"2018-10-11T09:18:46.339Z","hash":"QX5pTiYHtb"},{"temp":"26","hum":"26","duty":"512","lastEntry":"2018-10-11T09:19:01.761Z","hash":"6yACuW93TX"},{"temp":"26","hum":"26","duty":"512","lastEntry":"2018-10-11T09:19:17.174Z","hash":"7ZkkjommIc"},{"temp":"26","hum":"26","duty":"512","lastEntry":"2018-10-11T09:19:32.598Z","hash":"VRUs4xxeMR"},{"temp":"26","hum":"26","duty":"512","lastEntry":"2018-10-11T09:19:48.018Z","hash":"Lv2RIEocRB"},{"temp":"26","hum":"26","duty":"512","lastEntry":"2018-10-11T09:20:03.430Z","hash":"WoC5yDmmTs"}]
